jose_meu_pacote/__init__.cpython-311.pyc
jose_meu_pacote/__init__.py
jose_meu_pacote/modulo_exemplo.cpython-311.pyc
meu_pacote/__init__.cpython-311.pyc
meu_pacote/__init__.py
meu_pacote/modulo_exemplo.cpython-311.pyc
jose_meu_pacote-0.1.dist-info/METADATA
jose_meu_pacote-0.1.dist-info/WHEEL
jose_meu_pacote-0.1.dist-info/top_level.txt
jose_meu_pacote-0.1.dist-info/RECORD
