Metadata-Version: 2.1
Name: jose-meu-pacote
Version: 0.1
Summary: Um pacote com bytecode compilado
Classifier: Programming Language :: Python :: 3
Classifier: License :: OSI Approved :: MIT License
Classifier: Operating System :: OS Independent
Requires-Python: >=3.6
